sockjs/__init__.py
sockjs/constants.py
sockjs/exceptions.py
sockjs/protocol.py
sockjs/routing.py
sockjs/session.py
sockjs/transports/__init__.py
sockjs/transports/base.py
sockjs/transports/eventsource.py
sockjs/transports/htmlfile.py
sockjs/transports/jsonp.py
sockjs/transports/rawwebsocket.py
sockjs/transports/utils.py
sockjs/transports/websocket.py
sockjs/transports/xhr.py
sockjs/transports/xhrsend.py
sockjs/transports/xhrstreaming.py
sockjs_channels-0.1.2.dist-info/LICENSE
sockjs_channels-0.1.2.dist-info/METADATA
sockjs_channels-0.1.2.dist-info/WHEEL
sockjs_channels-0.1.2.dist-info/top_level.txt
sockjs_channels-0.1.2.dist-info/RECORD
