Metadata-Version: 2.1
Name: sockjs-channels
Version: 0.1.2
Summary: WebSocket emulation - SockJS server implementation for Django Channels.
Home-page: https://github.com/iTraceur/sockjs-channels
Author: iTraceur
Author-email: iTraceur.cn@gmail.com
License: MIT License
Classifier: Development Status :: 5 - Production/Stable
Classifier: Environment :: Web Environment
Classifier: Intended Audience :: Developers
Classifier: License :: OSI Approved :: MIT License
Classifier: Programming Language :: Python
Classifier: Programming Language :: Python :: 3
Classifier: Programming Language :: Python :: 3.6
Classifier: Programming Language :: Python :: 3.7
Classifier: Programming Language :: Python :: 3.8
Classifier: Programming Language :: Python :: 3.9
Classifier: Programming Language :: Python :: 3.10
Classifier: Framework :: Django
Classifier: Topic :: Internet :: WWW/HTTP
Requires: channels
Requires: django
Requires-Python: >=3.6.0
License-File: LICENSE
Requires-Dist: channels (>=3.0.0)
Requires-Dist: Django (>=3.2)
